evolutionary_tree_analyzer-1.1.0.dist-info/licenses/LICENSE
src/__init__.py
src/align_sequences.py
src/build_tree.py
src/fasta_parser.py
src/visualize_tree.py
evolutionary_tree_analyzer-1.1.0.dist-info/METADATA
evolutionary_tree_analyzer-1.1.0.dist-info/WHEEL
evolutionary_tree_analyzer-1.1.0.dist-info/entry_points.txt
evolutionary_tree_analyzer-1.1.0.dist-info/top_level.txt
evolutionary_tree_analyzer-1.1.0.dist-info/RECORD
