Metadata-Version: 2.4
Name: evolutionary-tree-analyzer
Version: 1.1.0
Summary: Build and visualize phylogenetic trees from FASTA files using parsimony and ML-style methods.
Home-page: https://github.com/B10ma3/evolutionary-tree-analyzer
Author: Mae Warner
Author-email: biology.mae@gmail.com
Classifier: Programming Language :: Python :: 3
Classifier: License :: OSI Approved :: MIT License
Classifier: Operating System :: OS Independent
Requires-Python: >=3.8
License-File: LICENSE
Requires-Dist: dash
Requires-Dist: dash-bootstrap-components
Requires-Dist: biopython
Requires-Dist: matplotlib
Requires-Dist: scipy
Requires-Dist: click
Dynamic: author
Dynamic: author-email
Dynamic: classifier
Dynamic: description
Dynamic: description-content-type
Dynamic: home-page
Dynamic: license-file
Dynamic: requires-dist
Dynamic: requires-python
Dynamic: summary
